<?xml version="1.0" encoding="UTF-8"?>
<GenRun Id="impl_1" LaunchPart="xc7a35tcpg236-1" LaunchTime="1571728398">
  <File Type="BITSTR-BMM" Name="twoBitAdder_bd.bmm"/>
  <File Type="OPT-METHODOLOGY-DRC" Name="twoBitAdder_methodology_drc_opted.rpt"/>
  <File Type="INIT-TIMING" Name="twoBitAdder_timing_summary_init.rpt"/>
  <File Type="ROUTE-PWR" Name="twoBitAdder_power_routed.rpt"/>
  <File Type="PA-TCL" Name="twoBitAdder.tcl"/>
  <File Type="OPT-TIMING" Name="twoBitAdder_timing_summary_opted.rpt"/>
  <File Type="OPT-DCP" Name="twoBitAdder_opt.dcp"/>
  <File Type="ROUTE-PWR-SUM" Name="twoBitAdder_power_summary_routed.pb"/>
  <File Type="REPORTS-TCL" Name="twoBitAdder_reports.tcl"/>
  <File Type="OPT-DRC" Name="twoBitAdder_drc_opted.rpt"/>
  <File Type="OPT-HWDEF" Name="twoBitAdder.hwdef"/>
  <File Type="PWROPT-DCP" Name="twoBitAdder_pwropt.dcp"/>
  <File Type="PWROPT-DRC" Name="twoBitAdder_drc_pwropted.rpt"/>
  <File Type="PWROPT-TIMING" Name="twoBitAdder_timing_summary_pwropted.rpt"/>
  <File Type="PLACE-DCP" Name="twoBitAdder_placed.dcp"/>
  <File Type="PLACE-IO" Name="twoBitAdder_io_placed.rpt"/>
  <File Type="PLACE-CLK" Name="twoBitAdder_clock_utilization_placed.rpt"/>
  <File Type="PLACE-UTIL" Name="twoBitAdder_utilization_placed.rpt"/>
  <File Type="PLACE-UTIL-PB" Name="twoBitAdder_utilization_placed.pb"/>
  <File Type="PLACE-CTRL" Name="twoBitAdder_control_sets_placed.rpt"/>
  <File Type="PLACE-SIMILARITY" Name="twoBitAdder_incremental_reuse_placed.rpt"/>
  <File Type="PLACE-PRE-SIMILARITY" Name="twoBitAdder_incremental_reuse_pre_placed.rpt"/>
  <File Type="BG-BGN" Name="twoBitAdder.bgn"/>
  <File Type="PLACE-TIMING" Name="twoBitAdder_timing_summary_placed.rpt"/>
  <File Type="POSTPLACE-PWROPT-DCP" Name="twoBitAdder_postplace_pwropt.dcp"/>
  <File Type="BG-BIN" Name="twoBitAdder.bin"/>
  <File Type="POSTPLACE-PWROPT-TIMING" Name="twoBitAdder_timing_summary_postplace_pwropted.rpt"/>
  <File Type="PHYSOPT-DCP" Name="twoBitAdder_physopt.dcp"/>
  <File Type="PHYSOPT-DRC" Name="twoBitAdder_drc_physopted.rpt"/>
  <File Type="BITSTR-MSK" Name="twoBitAdder.msk"/>
  <File Type="PHYSOPT-TIMING" Name="twoBitAdder_timing_summary_physopted.rpt"/>
  <File Type="ROUTE-ERROR-DCP" Name="twoBitAdder_routed_error.dcp"/>
  <File Type="ROUTE-DCP" Name="twoBitAdder_routed.dcp"/>
  <File Type="ROUTE-BLACKBOX-DCP" Name="twoBitAdder_routed_bb.dcp"/>
  <File Type="ROUTE-DRC" Name="twoBitAdder_drc_routed.rpt"/>
  <File Type="ROUTE-DRC-PB" Name="twoBitAdder_drc_routed.pb"/>
  <File Type="BITSTR-LTX" Name="debug_nets.ltx"/>
  <File Type="BITSTR-LTX" Name="twoBitAdder.ltx"/>
  <File Type="ROUTE-DRC-RPX" Name="twoBitAdder_drc_routed.rpx"/>
  <File Type="BITSTR-MMI" Name="twoBitAdder.mmi"/>
  <File Type="ROUTE-METHODOLOGY-DRC" Name="twoBitAdder_methodology_drc_routed.rpt"/>
  <File Type="ROUTE-METHODOLOGY-DRC-RPX" Name="twoBitAdder_methodology_drc_routed.rpx"/>
  <File Type="BITSTR-SYSDEF" Name="twoBitAdder.sysdef"/>
  <File Type="ROUTE-METHODOLOGY-DRC-PB" Name="twoBitAdder_methodology_drc_routed.pb"/>
  <File Type="ROUTE-PWR-RPX" Name="twoBitAdder_power_routed.rpx"/>
  <File Type="ROUTE-STATUS" Name="twoBitAdder_route_status.rpt"/>
  <File Type="ROUTE-STATUS-PB" Name="twoBitAdder_route_status.pb"/>
  <File Type="ROUTE-TIMINGSUMMARY" Name="twoBitAdder_timing_summary_routed.rpt"/>
  <File Type="ROUTE-TIMING-PB" Name="twoBitAdder_timing_summary_routed.pb"/>
  <File Type="ROUTE-TIMING-RPX" Name="twoBitAdder_timing_summary_routed.rpx"/>
  <File Type="ROUTE-SIMILARITY" Name="twoBitAdder_incremental_reuse_routed.rpt"/>
  <File Type="ROUTE-CLK" Name="twoBitAdder_clock_utilization_routed.rpt"/>
  <File Type="ROUTE-BUS-SKEW" Name="twoBitAdder_bus_skew_routed.rpt"/>
  <File Type="ROUTE-BUS-SKEW-PB" Name="twoBitAdder_bus_skew_routed.pb"/>
  <File Type="ROUTE-BUS-SKEW-RPX" Name="twoBitAdder_bus_skew_routed.rpx"/>
  <File Type="POSTROUTE-PHYSOPT-DCP" Name="twoBitAdder_postroute_physopt.dcp"/>
  <File Type="POSTROUTE-PHYSOPT-BLACKBOX-DCP" Name="twoBitAdder_postroute_physopt_bb.dcp"/>
  <File Type="POSTROUTE-PHYSOPT-TIMING" Name="twoBitAdder_timing_summary_postroute_physopted.rpt"/>
  <File Type="POSTROUTE-PHYSOPT-TIMING-PB" Name="twoBitAdder_timing_summary_postroute_physopted.pb"/>
  <File Type="POSTROUTE-PHYSOPT-TIMING-RPX" Name="twoBitAdder_timing_summary_postroute_physopted.rpx"/>
  <File Type="POSTROUTE-PHYSOPT-BUS-SKEW" Name="twoBitAdder_bus_skew_postroute_physopted.rpt"/>
  <File Type="POSTROUTE-PHYSOPT-BUS-SKEW-PB" Name="twoBitAdder_bus_skew_postroute_physopted.pb"/>
  <File Type="BG-BIT" Name="twoBitAdder.bit"/>
  <File Type="POSTROUTE-PHYSOPT-BUS-SKEW-RPX" Name="twoBitAdder_bus_skew_postroute_physopted.rpx"/>
  <File Type="BITSTR-RBT" Name="twoBitAdder.rbt"/>
  <File Type="BITSTR-NKY" Name="twoBitAdder.nky"/>
  <File Type="BG-DRC" Name="twoBitAdder.drc"/>
  <File Type="RDI-RDI" Name="twoBitAdder.vdi"/>
  <File Type="WBT-USG" Name="usage_statistics_webtalk.html"/>
  <FileSet Name="sources" Type="DesignSrcs" RelSrcDir="$PSRCDIR/sources_1">
    <Filter Type="Srcs"/>
    <File Path="$PSRCDIR/sources_1/new/twoBitAdder.sv">
      <FileInfo>
        <Attr Name="UsedIn" Val="synthesis"/>
        <Attr Name="UsedIn" Val="implementation"/>
        <Attr Name="UsedIn" Val="simulation"/>
      </FileInfo>
    </File>
    <Config>
      <Option Name="DesignMode" Val="RTL"/>
      <Option Name="TopModule" Val="twoBitAdder"/>
    </Config>
  </FileSet>
  <FileSet Name="constrs_in" Type="Constrs" RelSrcDir="$PSRCDIR/constrs_1">
    <Filter Type="Constrs"/>
    <File Path="$PPRDIR/../../../University/Year 2/Digital Design CS223/Lab/Basys Vivado/Basys3.xdc">
      <FileInfo>
        <Attr Name="UsedIn" Val="synthesis"/>
        <Attr Name="UsedIn" Val="implementation"/>
      </FileInfo>
    </File>
    <Config>
      <Option Name="ConstrsType" Val="XDC"/>
    </Config>
  </FileSet>
  <FileSet Name="utils" Type="Utils" RelSrcDir="$PSRCDIR/utils_1">
    <Filter Type="Utils"/>
    <Config>
      <Option Name="TopAutoSet" Val="TRUE"/>
    </Config>
  </FileSet>
  <Strategy Version="1" Minor="2">
    <StratHandle Name="Vivado Implementation Defaults" Flow="Vivado Implementation 2019">
      <Desc>Default settings for Implementation.</Desc>
    </StratHandle>
    <Step Id="init_design"/>
    <Step Id="opt_design"/>
    <Step Id="power_opt_design"/>
    <Step Id="place_design"/>
    <Step Id="post_place_power_opt_design"/>
    <Step Id="phys_opt_design"/>
    <Step Id="route_design"/>
    <Step Id="post_route_phys_opt_design"/>
    <Step Id="write_bitstream">
      <Option Id="BinFile">1</Option>
    </Step>
  </Strategy>
</GenRun>
